{"nodes": [{"id": "home_federico_documentos_lubricentro_pages_3_productos_py", "label": "3_Productos.py", "file_type": "code", "source_file": "pages/3_Productos.py", "source_location": "L1"}], "edges": [{"source": "home_federico_documentos_lubricentro_pages_3_productos_py", "target": "streamlit", "relation": "imports", "context": "import", "confidence": "EXTRACTED", "source_file": "pages/3_Productos.py", "source_location": "L1", "weight": 1.0}, {"source": "home_federico_documentos_lubricentro_pages_3_productos_py", "target": "database", "relation": "imports", "context": "import", "confidence": "EXTRACTED", "source_file": "pages/3_Productos.py", "source_location": "L2", "weight": 1.0}], "raw_calls": []}